[{"date": "2026-04-03_1826", "displayDate": "2026-04-03", "displayTime": "18:26", "sentiment": "neutral", "sentimentLabel": "中性", "sentimentIcon": "→", "summary": "维持 Hold（持有/观望）评级。 当前市场处于“矛盾累积期”，基本面的估值底与技术面的趋势顶激烈对抗。虽然远期市盈率处于历史低位且单季度现金流改善，但净利润暴跌及销售费用效率恶化构成显著风险。建议维持底仓，严禁左侧激进加仓，设定$110 为硬性止损位，等待右侧趋势确认信号。", "signals": [], "analystReports": ["基本面", "市场", "新闻", "情绪"], "reportPath": "./history/2026-04-03_1826/"}, {"date": "2026-04-03_0718", "displayDate": "2026-04-03", "displayTime": "07:18", "sentiment": "bear", "sentimentLabel": "看空", "sentimentIcon": "↓", "summary": "坚决卖出/规避风险。尽管公司拥有巨额现金储备且估值处于低位，但财务质量出现严重恶化信号（应收账款激增与营收背离、现金流暴跌），叠加技术面空头趋势确立，当前介入属于高风险的“接飞刀”行为。建议清理现有头寸，等待基本面右侧信号。", "signals": [], "analystReports": ["基本面", "市场", "新闻", "情绪"], "reportPath": "./history/2026-04-03_0718/"}, {"date": "2026-04-02_1715", "displayDate": "2026-04-02", "displayTime": "17:15", "sentiment": "bull", "sentimentLabel": "看多", "sentimentIcon": "↑", "summary": "决策：买入建仓（Buy）", "signals": [], "analystReports": ["基本面", "市场", "新闻", "情绪"], "reportPath": "./history/2026-04-02_1715/"}, {"date": "2026-04-01_1652", "displayDate": "2026-04-01", "displayTime": "16:52", "sentiment": "bear", "sentimentLabel": "看空", "sentimentIcon": "↓", "summary": "决策评级：持有（Hold）—— 执行减半仓位风控", "signals": [], "analystReports": ["基本面", "市场", "新闻", "情绪"], "reportPath": "./history/2026-04-01_1652/"}, {"date": "2026-03-30_0656", "displayDate": "2026-03-30", "displayTime": "06:56", "sentiment": "bull", "sentimentLabel": "看多", "sentimentIcon": "↑", "summary": "决策：逢低分批买入（防御性左侧布局）", "signals": [], "analystReports": ["基本面", "市场", "新闻", "情绪"], "reportPath": "./history/2026-03-30_0656/"}, {"date": "2026-03-27_1757", "displayDate": "2026-03-27", "displayTime": "17:57", "sentiment": "bull", "sentimentLabel": "看多", "sentimentIcon": "↑", "summary": "建议买入（BUY），但需执行修正后的分批建仓策略。当前估值处于历史底部且政策面出现利好催化剂，具备左侧布局价值。鉴于技术面存在死亡交叉风险，建议初始仓位控制在 20%，采取“左侧底仓 + 右侧确认”的分步入场方式，严格设置止损以管理波动风险。", "signals": [], "analystReports": ["基本面", "市场", "新闻", "情绪"], "reportPath": "./history/2026-03-27_1757/"}, {"date": "2026-03-27_0656", "displayDate": "2026-03-27", "displayTime": "06:56", "sentiment": "bear", "sentimentLabel": "看空", "sentimentIcon": "↓", "summary": "决策：卖出/大幅减仓", "signals": [], "analystReports": ["基本面", "市场", "新闻", "情绪"], "reportPath": "./history/2026-03-27_0656/"}, {"date": "2026-03-26_1758", "displayDate": "2026-03-26", "displayTime": "17:58", "sentiment": "bull", "sentimentLabel": "看多", "sentimentIcon": "↑", "summary": "决策：买入（试探性建仓）", "signals": [], "analystReports": ["基本面", "市场", "新闻", "情绪"], "reportPath": "./history/2026-03-26_1758/"}, {"date": "2026-03-26_0631", "displayDate": "2026-03-26", "displayTime": "06:31", "sentiment": "bull", "sentimentLabel": "看多", "sentimentIcon": "↑", "summary": "决策：买入", "signals": [], "analystReports": ["基本面", "市场", "新闻", "情绪"], "reportPath": "./history/2026-03-26_0631/"}, {"date": "2026-03-25_1734", "displayDate": "2026-03-25", "displayTime": "17:34", "sentiment": "bear", "sentimentLabel": "看空", "sentimentIcon": "↓", "summary": "决策：观望（防御性持仓）", "signals": [], "analystReports": ["基本面", "市场", "新闻", "情绪"], "reportPath": "./history/2026-03-25_1734/"}, {"date": "2026-03-25_1643", "displayDate": "2026-03-25", "displayTime": "16:43", "sentiment": "bull", "sentimentLabel": "看多", "sentimentIcon": "↑", "summary": "决策：买入（分批建仓）", "signals": [], "analystReports": ["基本面", "市场", "新闻", "情绪"], "reportPath": "./history/2026-03-25_1643/"}, {"date": "2026-03-25_1232", "displayDate": "2026-03-25", "displayTime": "12:32", "sentiment": "bull", "sentimentLabel": "看多", "sentimentIcon": "↑", "summary": "决策：买入（审慎左侧布局）", "signals": [], "analystReports": ["基本面", "市场", "新闻", "情绪"], "reportPath": "./history/2026-03-25_1232/"}, {"date": "2026-03-24_1834", "displayDate": "2026-03-24", "displayTime": "18:34", "sentiment": "bull", "sentimentLabel": "看多", "sentimentIcon": "↑", "summary": "建议买入（修正后的分批建仓策略）。当前市场估值未能充分反映云业务增长及 AI 转型价值，且巨额现金储备提供了极高的安全边际。鉴于技术面仍处于空头趋势（死亡交叉）且基本面存在现金流恶化风险，建议采取“左侧试错，右侧加仓”策略。初始仓位控制在 15%，设置$115 硬止损，将单笔交易账户风险控制在 1.35% 以内，盈亏比约为 3:1。", "signals": [], "analystReports": ["基本面", "市场", "新闻", "情绪"], "reportPath": "./history/2026-03-24_1834/"}]