[{"date":"2026-03-24_1910","displayDate":"2026-03-24","sentiment":"bull","sentimentLabel":"看多","sentimentIcon":"↑","summary":"决策：买入（谨慎）","signals":[],"reportPath":"./history/2026-03-24_1910/"},{"date":"2026-03-25_1100","displayDate":"2026-03-25","sentiment":"neutral","sentimentLabel":"中性","sentimentIcon":"→","summary":"维持 Hold（观望）评级，严守仓位红线。","signals":[],"reportPath":"./history/2026-03-25_1100/"},{"date":"2026-03-25_1206","displayDate":"2026-03-25","sentiment":"bull","sentimentLabel":"看多","sentimentIcon":"↑","summary":"建议买入（Buy）**，初始仓位建议 **20%**。当前股价（¥93.33）处于估值底部区域，基本面强劲（净利润 +112.8%，现金储备充足）提供了坚实的安","signals":[],"reportPath":"./history/2026-03-25_1206/"}]
