[{"date": "2026-04-06_0600", "displayDate": "2026-04-06", "displayTime": "06:00", "sentiment": "bull", "sentimentLabel": "看多", "sentimentIcon": "↑", "summary": "建议操作：买入", "signals": [], "analystReports": ["基本面", "市场", "新闻", "情绪"], "reportPath": "./history/2026-04-06_0600/"}, {"date": "2026-04-03_1700", "displayDate": "2026-04-03", "displayTime": "17:00", "sentiment": "bear", "sentimentLabel": "看空", "sentimentIcon": "↓", "summary": "坚决卖出/清仓。基于风险管理部门最终裁定，当前标的存在严重的数据完整性风险（个股代码与指数数据错配），且技术面呈现空头加速形态。在数据混乱与趋势走坏的双重压力下，持有现金是唯一正解，严禁左侧博弈。", "signals": [], "analystReports": ["基本面", "市场", "新闻", "情绪"], "reportPath": "./history/2026-04-03_1700/"}, {"date": "2026-04-03_0600", "displayDate": "2026-04-03", "displayTime": "06:00", "sentiment": "bear", "sentimentLabel": "看空", "sentimentIcon": "↓", "summary": "坚决卖出 / 清仓观望。尽管宏观面存在地缘政治缓和的潜在利好，但技术面“死亡交叉”带来的系统性风险不容忽视。在信号冲突且高波动环境下，本金安全优于潜在收益，建议执行最彻底的风险出清，严禁左侧抄底或盲目做空。", "signals": [], "analystReports": ["基本面", "市场", "新闻", "情绪"], "reportPath": "./history/2026-04-03_0600/"}, {"date": "2026-04-02_1700", "displayDate": "2026-04-02", "displayTime": "17:00", "sentiment": "bear", "sentimentLabel": "看空", "sentimentIcon": "↓", "summary": "坚决卖出，防御为主。", "signals": [], "analystReports": ["基本面", "市场", "新闻", "情绪"], "reportPath": "./history/2026-04-02_1700/"}, {"date": "2026-04-02_1535", "displayDate": "2026-04-02", "displayTime": "15:35", "sentiment": "bear", "sentimentLabel": "看空", "sentimentIcon": "↓", "summary": "卖出/持币观望。建议立即执行卖出操作将仓位降至 0%，若当前为空仓则继续保持空仓。拒绝在 3850 点支撑位进行左侧抄底，必须等待右侧确认信号（趋势反转、动能确认、风险消除）出现后方可考虑入场。当前市场环境下，现金是防范极端风险的战略资产。", "signals": [], "analystReports": ["基本面", "市场", "新闻", "情绪"], "reportPath": "./history/2026-04-02_1535/"}, {"date": "2026-04-01_1549", "displayDate": "2026-04-01", "displayTime": "15:49", "sentiment": "bull", "sentimentLabel": "看多", "sentimentIcon": "↑", "summary": "决策：买入（左侧分批建仓）", "signals": [], "analystReports": ["基本面", "市场", "新闻", "情绪"], "reportPath": "./history/2026-04-01_1549/"}, {"date": "2026-03-30_0600", "displayDate": "2026-03-30", "displayTime": "06:00", "sentiment": "bull", "sentimentLabel": "看多", "sentimentIcon": "↑", "summary": "建议买入。基于风险收益比的逆向投资决策，当前价格距离关键长期支撑位（200 日均线）仅约 2% 空间，而潜在上行空间超过 7%，盈亏比优于 1:3。尽管存在数据噪音和中期动能疲弱风险，但长期牛市架构未坏，建议采取“左侧交易 + 右侧确认”策略分批建仓。", "signals": [], "analystReports": ["基本面", "市场", "新闻", "情绪"], "reportPath": "./history/2026-03-30_0600/"}, {"date": "2026-03-27_1700", "displayDate": "2026-03-27", "displayTime": "17:00", "sentiment": "bear", "sentimentLabel": "看空", "sentimentIcon": "↓", "summary": "坚决卖出/清仓。当前市场环境下，保住本金的安全边际远高于博弈潜在反弹的收益。建议明日开盘清空所有上证指数相关风险敞口，资金转入低风险货币基金或国债逆回购，等待右侧明确信号。", "signals": [], "analystReports": ["基本面", "市场", "新闻", "情绪"], "reportPath": "./history/2026-03-27_1700/"}, {"date": "2026-03-27_0600", "displayDate": "2026-03-27", "displayTime": "06:00", "sentiment": "bear", "sentimentLabel": "看空", "sentimentIcon": "↓", "summary": "决策：持有（HOLD）", "signals": [], "analystReports": ["基本面", "市场", "新闻", "情绪"], "reportPath": "./history/2026-03-27_0600/"}, {"date": "2026-03-26_1700", "displayDate": "2026-03-26", "displayTime": "17:00", "sentiment": "bear", "sentimentLabel": "看空", "sentimentIcon": "↓", "summary": "建议操作：持有现金/观望（Hold），现有仓位减仓 20%-30%", "signals": [], "analystReports": ["基本面", "市场", "新闻", "情绪"], "reportPath": "./history/2026-03-26_1700/"}, {"date": "2026-03-25_1700", "displayDate": "2026-03-25", "displayTime": "17:00", "sentiment": "bull", "sentimentLabel": "看多", "sentimentIcon": "↑", "summary": "决策：买入（分批建仓）", "signals": [], "analystReports": ["基本面", "市场", "新闻", "情绪"], "reportPath": "./history/2026-03-25_1700/"}, {"date": "2026-03-25_1134", "displayDate": "2026-03-25", "displayTime": "11:34", "sentiment": "bear", "sentimentLabel": "看空", "sentimentIcon": "↓", "summary": "坚决卖出 / 清仓观望", "signals": [], "analystReports": ["基本面", "市场", "新闻", "情绪"], "reportPath": "./history/2026-03-25_1134/"}]